CHANGES.rst
INSTALL.txt
LICENSE
MANIFEST.in
README.rst
REQUIREMENTS
setup.cfg
setup.py
docs/Makefile
docs/ammonia_model.rst
docs/baseline.rst
docs/basic_plot.py
docs/classes.rst
docs/classfiles.rst
docs/conf.py
docs/cubes.rst
docs/example_LTE.rst
docs/example_LTE_lineforest.py
docs/example_MUSE.rst
docs/example_NIR_cube.rst
docs/example_continuum_fromscratch.py
docs/example_continuum_fromscratch.rst
docs/example_cube_fromscratch.rst
docs/example_fromscratch.py
docs/example_fromscratch.rst
docs/example_h2co.rst
docs/example_h2co_mm.rst
docs/example_hcn.rst
docs/example_hcop.py
docs/example_hcop.rst
docs/example_minimal_cube.rst
docs/example_n2hp.rst
docs/example_n2hp_cube.rst
docs/example_nh3.rst
docs/example_nh3_cube.rst
docs/example_o-nh2d.rst
docs/example_p-nh2d.rst
docs/example_pymc.rst
docs/example_pymc_ammonia.rst
docs/example_sdss.py
docs/example_sdss.rst
docs/example_sn.rst
docs/example_template.rst
docs/example_vega_echelle.rst
docs/examples.rst
docs/faq.rst
docs/features.rst
docs/fit_custom_model.rst
docs/fitsfiles.rst
docs/fitting.rst
docs/formaldehyde_model.rst
docs/gaussian_model.rst
docs/gbtfiles.rst
docs/guide_class.rst
docs/guide_iraf.rst
docs/hcn_model.rst
docs/hdf5files.rst
docs/hill5infall_model.rst
docs/hydrogen_model.rst
docs/hyperfine_model.rst
docs/index.rst
docs/install.rst
docs/install_via_GitHub.rst
docs/interactive.rst
docs/logo.png
docs/lte_molecule_model.rst
docs/make.bat
docs/measurements.rst
docs/modelgrid.rst
docs/models.rst
docs/n2hp_model.rst
docs/nh3_tau.rst
docs/parameters.rst
docs/plotting.rst
docs/projects.rst
docs/pyspeckit_manual.tex
docs/readers.rst
docs/registration.rst
docs/rtd-pip-requirements
docs/spectrum.rst
docs/template_model.rst
docs/txtfiles.rst
docs/units.rst
docs/voigt_model.rst
docs/wrappers.rst
docs/_static/astropy.css
docs/_static/extra.css
docs/_static/scipy.css
docs/_templates/layout.html
docs/images/LTE_w51.png
docs/images/SN2009ip_UT121002_Halpha_voigt_threecomp.png
pyspeckit.egg-info/PKG-INFO
pyspeckit.egg-info/SOURCES.txt
pyspeckit.egg-info/dependency_links.txt
pyspeckit.egg-info/not-zip-safe
pyspeckit.egg-info/requires.txt
pyspeckit.egg-info/top_level.txt
